neet_cli/__init__.py
neet_cli/main.py
neet_cli/problems_data.py
neet_cli-0.1.0.dist-info/METADATA
neet_cli-0.1.0.dist-info/WHEEL
neet_cli-0.1.0.dist-info/entry_points.txt
neet_cli-0.1.0.dist-info/RECORD
