Metadata-Version: 2.1
Name: neet-cli
Version: 0.1.0
Summary: 
Author: Eliel
Author-email: eliel.hj90@gmail.com
Requires-Python: >=3.11,<4.0
Classifier: Programming Language :: Python :: 3
Classifier: Programming Language :: Python :: 3.11
Requires-Dist: typer[all] (>=0.7.0,<0.8.0)
